hyperscale/stax/cli.py
hyperscale/stax/core.py
hyperscale/stax/manifest.py
hyperscale/stax/sigstore.py
hyperscale_stax-0.4.1.dist-info/METADATA
hyperscale_stax-0.4.1.dist-info/WHEEL
hyperscale_stax-0.4.1.dist-info/entry_points.txt
hyperscale_stax-0.4.1.dist-info/licenses/LICENSE
hyperscale_stax-0.4.1.dist-info/RECORD
